moss_crewai/__init__.py
moss_crewai/interceptor.py
moss_crewai/signing.py
moss_crewai/wrapper.py
moss_crewai-1.0.0.dist-info/METADATA
moss_crewai-1.0.0.dist-info/WHEEL
moss_crewai-1.0.0.dist-info/licenses/LICENSE
moss_crewai-1.0.0.dist-info/RECORD
