Metadata-Version: 2.4
Name: moss-crewai
Version: 1.0.0
Summary: MOSS cryptographic signing integration for CrewAI
Project-URL: Homepage, https://mosscomputing.com
Project-URL: Documentation, https://mosscomputing.com/docs
Project-URL: Repository, https://github.com/mosscomputing/moss-crewai
Author-email: IAMPASS Technologies <moss@iampass.com>
License: BSL-1.1
License-File: LICENSE
Keywords: ai-agents,crewai,cryptography,moss,security,signing
Classifier: Development Status :: 4 - Beta
Classifier: Intended Audience :: Developers
Classifier: License :: Other/Proprietary License
Classifier: Programming Language :: Python :: 3
Classifier: Programming Language :: Python :: 3.9
Classifier: Programming Language :: Python :: 3.10
Classifier: Programming Language :: Python :: 3.11
Classifier: Programming Language :: Python :: 3.12
Requires-Python: >=3.9
Requires-Dist: crewai>=0.1.0
Requires-Dist: moss-sdk>=1.0.0
Provides-Extra: dev
Requires-Dist: pytest-asyncio>=0.21.0; extra == 'dev'
Requires-Dist: pytest>=7.0.0; extra == 'dev'
Requires-Dist: ruff>=0.1.0; extra == 'dev'
